lunar_mcp_server/__init__.py
lunar_mcp_server/auspicious_dates.py
lunar_mcp_server/bazi.py
lunar_mcp_server/calendar_conversions.py
lunar_mcp_server/festivals.py
lunar_mcp_server/lunar_calculations.py
lunar_mcp_server/server.py
lunar_mcp_server/cultural_data/__init__.py
lunar_mcp_server/cultural_data/chinese.py
lunar_mcp_server-1.2.0.dist-info/METADATA
lunar_mcp_server-1.2.0.dist-info/WHEEL
lunar_mcp_server-1.2.0.dist-info/entry_points.txt
lunar_mcp_server-1.2.0.dist-info/licenses/LICENSE
lunar_mcp_server-1.2.0.dist-info/RECORD
