Metadata-Version: 2.4
Name: lunar-mcp-server
Version: 1.2.0
Summary: A comprehensive Chinese Lunar Calendar MCP server providing traditional Chinese lunar calendar information, auspicious date checking, and festival data
Project-URL: Homepage, https://github.com/AngusHsu/lunar-mcp-server
Project-URL: Repository, https://github.com/AngusHsu/lunar-mcp-server
Project-URL: Documentation, https://github.com/AngusHsu/lunar-mcp-server#readme
Project-URL: Bug Tracker, https://github.com/AngusHsu/lunar-mcp-server/issues
Project-URL: Changelog, https://github.com/AngusHsu/lunar-mcp-server/blob/main/CHANGELOG.md
Author: Lunar MCP Team
License: MIT
License-File: LICENSE
Keywords: almanac,auspicious,calendar,chinese,festival,five-elements,fortune,lunar,mcp,model-context-protocol,moon-phase,zodiac
Classifier: Development Status :: 4 - Beta
Classifier: Intended Audience :: Developers
Classifier: License :: OSI Approved :: MIT License
Classifier: Programming Language :: Python :: 3
Classifier: Programming Language :: Python :: 3.11
Classifier: Programming Language :: Python :: 3.12
Classifier: Topic :: Religion
Classifier: Topic :: Scientific/Engineering :: Astronomy
Classifier: Topic :: Software Development :: Libraries :: Python Modules
Classifier: Topic :: Utilities
Requires-Python: >=3.11
Requires-Dist: astropy>=6.0.0
Requires-Dist: chinese-calendar>=1.9.0
Requires-Dist: ephem>=4.1.5
Requires-Dist: lunardate>=0.2.2
Requires-Dist: mcp>=1.0.0
Requires-Dist: pydantic>=2.5.0
Requires-Dist: python-dateutil>=2.8.2
Requires-Dist: pytz>=2023.3
Requires-Dist: skyfield>=1.48
Requires-Dist: typing-extensions>=4.8.0
Requires-Dist: zhdate>=0.1
Provides-Extra: dev
Requires-Dist: black>=23.0.0; extra == 'dev'
Requires-Dist: isort>=5.12.0; extra == 'dev'
Requires-Dist: mypy>=1.6.0; extra == 'dev'
Requires-Dist: pre-commit>=3.5.0; extra == 'dev'
Requires-Dist: pytest-asyncio>=0.21.0; extra == 'dev'
Requires-Dist: pytest-cov>=4.1.0; extra == 'dev'
Requires-Dist: pytest>=7.4.0; extra == 'dev'
Requires-Dist: ruff>=0.1.0; extra == 'dev'
